LICENSE
MANIFEST.in
README.rst
setup.cfg
setup.py
scripts/echo_ubik_conf
scripts/ubik
scripts/ubik-package
scripts/ubik-repo
scripts/ubik-web
ubik/__init__.py
ubik/cli.py
ubik/conf.py
ubik/core.py
ubik/database.py
ubik/downloader.py
ubik/exceptions.py
ubik/installer.py
ubik/logger.py
ubik/package.py
ubik/reinstaller.py
ubik/remover.py
ubik/status.py
ubik/tools.py
ubik/upgrader.py
ubik/view.py
ubik.egg-info/PKG-INFO
ubik.egg-info/SOURCES.txt
ubik.egg-info/dependency_links.txt
ubik.egg-info/requires.txt
ubik.egg-info/top_level.txt
ubik/web/__init__.py
ubik/web/auth.py
ubik/web/helpers.py
ubik/web/logs.py
ubik/web/views.py
ubik/web/websocket.py
ubik/web/static/css/bootstrap-responsive.css
ubik/web/static/css/bootstrap-responsive.min.css
ubik/web/static/css/bootstrap.css
ubik/web/static/css/bootstrap.min.css
ubik/web/static/img/glyphicons-halflings-white.png
ubik/web/static/img/glyphicons-halflings.png
ubik/web/static/js/bootstrap.js
ubik/web/static/js/bootstrap.min.js
ubik/web/static/js/jquery-1.8.2.min.js
ubik/web/templates/index.html
ubik/web/templates/info.html
ubik/web/templates/layout.html
ubik/web/templates/login.html
ubik/web/templates/stats.html
ubik_toolbelt/__init__.py
ubik_toolbelt/control.py
ubik_toolbelt/logger.py
ubik_toolbelt/package.py
ubik_toolbelt/repo.py
ubik_toolbelt/serve.py
ubik_toolbelt/contrib/__init__.py
ubik_toolbelt/contrib/utils.py