Metadata-Version: 1.1
Name: ubik
Version: 0.2.7
Summary: Minimal and elegant packages manager
Home-page: https://github.com/toxinu/ubik/
Author: toxinu
Author-email: toxinu@gmail.com
License: Ubik
